pysdcp_extended/__init__.py
pysdcp_extended/protocol.py
pysdcp_extended-0.2.0.dist-info/LICENSE.md
pysdcp_extended-0.2.0.dist-info/METADATA
pysdcp_extended-0.2.0.dist-info/WHEEL
pysdcp_extended-0.2.0.dist-info/RECORD
