Metadata-Version: 2.3
Name: pysdcp-extended
Version: 0.2.0
Summary: Extended SDCP / PJ Talk library to control Sony projectors
License: MIT
Keywords: sdcp,pjtalk,sony,projector,ip-control,home-automation
Author: kennymc.c
Requires-Python: >=3.11,<4.0
Classifier: Development Status :: 4 - Beta
Classifier: Intended Audience :: Developers
Classifier: License :: OSI Approved :: MIT License
Classifier: Operating System :: OS Independent
Classifier: Programming Language :: Python :: 3
Classifier: Programming Language :: Python :: 3.11
Classifier: Programming Language :: Python :: 3.12
Classifier: Programming Language :: Python :: 3.13
Classifier: Topic :: Home Automation
Classifier: Topic :: Software Development :: Libraries
Project-URL: Repository, https://github.com/kennymc-c/pySDCP-extended
